skydog_option/__init__.py
skydog_option/cboe.py
skydog_option/hkex.py
skydog_finance-0.0.14.dist-info/LICENSE
skydog_finance-0.0.14.dist-info/METADATA
skydog_finance-0.0.14.dist-info/WHEEL
skydog_finance-0.0.14.dist-info/top_level.txt
skydog_finance-0.0.14.dist-info/RECORD
