Metadata-Version: 2.1
Name: skydog-finance
Version: 0.0.14
Summary: Skydog Ventures finance lib
Home-page: https://github.com/myskydog/skydog_finance
Author: Terry Wu
Author-email: myskydog@gmail.com
License: UNKNOWN
Project-URL: Bug Tracker, https://github.com/myskydog/skydog_finance/issues
Platform: UNKNOWN
Classifier: Programming Language :: Python :: 3
Classifier: License :: OSI Approved :: MIT License
Classifier: Operating System :: OS Independent
Requires-Python: >=3.6
License-File: LICENSE
